{"@context": ["https://www.w3.org/ns/activitystreams", "https://w3id.org/security/v1", {"manuallyApprovesFollowers": "as:manuallyApprovesFollowers", "sensitive": "as:sensitive", "movedTo": "as:movedTo", "Hashtag": "as:Hashtag", "ostatus": "http://ostatus.org#", "atomUri": "ostatus:atomUri", "inReplyToAtomUri": "ostatus:inReplyToAtomUri", "conversation": "ostatus:conversation", "toot": "http://joinmastodon.org/ns#", "Emoji": "toot:Emoji"}], "id": "https://mstdn.maud.io/users/Otakan951/statuses/6454114", "type": "Note", "summary": null, "content": "<p>\u56fa\u307e\u3063\u305f\u5f8c <a href=\"https://mstdn.maud.io/media/J91WZbCoiNQ2oXv7mCY\" rel=\"nofollow noopener\" target=\"_blank\"><span class=\"invisible\">https://</span><span class=\"ellipsis\">mstdn.maud.io/media/J91WZbCoiN</span><span class=\"invisible\">Q2oXv7mCY</span></a></p>", "inReplyTo": null, "published": "2017-09-11T11:16:41Z", "url": "https://mstdn.maud.io/@Otakan951/6454114", "attributedTo": "https://mstdn.maud.io/users/Otakan951", "to": ["https://www.w3.org/ns/activitystreams#Public"], "cc": ["https://mstdn.maud.io/users/Otakan951/followers"], "sensitive": false, "atomUri": "https://mstdn.maud.io/users/Otakan951/statuses/6454114", "inReplyToAtomUri": null, "conversation": "tag:mstdn.maud.io,2017-09-11:objectId=3583861:objectType=Conversation", "attachment": [{"type": "Document", "mediaType": "image/png", "url": "https://mstdn.maud.io/system/media_attachments/files/000/471/105/original/2287bff9a0d46c21.png", "name": null}], "tag": []}